sphinxcontrib/kasane/__init__.py
sphinxcontrib/kasane/conditions.py
sphinxcontrib/kasane/inheritance.py
sphinxcontrib_extdevhelper_kasane-0.2.1.dist-info/licenses/LICENSE
sphinxcontrib_extdevhelper_kasane-0.2.1.dist-info/METADATA
sphinxcontrib_extdevhelper_kasane-0.2.1.dist-info/WHEEL
sphinxcontrib_extdevhelper_kasane-0.2.1.dist-info/top_level.txt
sphinxcontrib_extdevhelper_kasane-0.2.1.dist-info/RECORD
