Metadata-Version: 2.4
Name: sphinxcontrib-extdevhelper-kasane
Version: 0.2.1
Summary: 襲 - Provide dynamic inheritance shortcuts to make Sphinx extension development easier
Author-email: nikkie <takuyafjp+develop@gmail.com>
License: MIT License
Project-URL: Repository, https://github.com/ftnext/sphinxcontrib-extdevhelper-kasane
Keywords: Sphinx extension,helper
Classifier: Development Status :: 3 - Alpha
Classifier: Intended Audience :: Developers
Classifier: Framework :: Sphinx
Classifier: Framework :: Sphinx :: Extension
Classifier: Topic :: Documentation
Classifier: Topic :: Documentation :: Sphinx
Classifier: Topic :: Software Development :: Documentation
Classifier: Programming Language :: Python
Classifier: Programming Language :: Python :: 3
Classifier: Programming Language :: Python :: 3 :: Only
Classifier: Programming Language :: Python :: 3.10
Classifier: Programming Language :: Python :: 3.11
Classifier: Programming Language :: Python :: 3.12
Classifier: Programming Language :: Python :: 3.13
Classifier: Programming Language :: Python :: 3.14
Requires-Python: >=3.8
License-File: LICENSE
Requires-Dist: Sphinx
Provides-Extra: dev
Requires-Dist: taskipy; extra == "dev"
Requires-Dist: autoflake; extra == "dev"
Requires-Dist: pyupgrade; extra == "dev"
Requires-Dist: black; extra == "dev"
Requires-Dist: isort; extra == "dev"
Requires-Dist: pytest; extra == "dev"
Requires-Dist: pytest-randomly; extra == "dev"
Requires-Dist: flake8; extra == "dev"
Requires-Dist: mypy; extra == "dev"
Dynamic: license-file
